simpelmin/__init__.py
simpelmin/apps.py
simpelmin/atomics.py
simpelmin/components.py
simpelmin/tests.py
simpelmin/version.py
simpelmin/migrations/__init__.py
simpelmin/static/simpelmin/css/main.bundle.css
simpelmin/static/simpelmin/css/plugins/swiper.min.css
simpelmin/static/simpelmin/fonts/materialdesignicons-webfont.eot
simpelmin/static/simpelmin/fonts/materialdesignicons-webfont.ttf
simpelmin/static/simpelmin/fonts/materialdesignicons-webfont.woff
simpelmin/static/simpelmin/fonts/materialdesignicons-webfont.woff2
simpelmin/static/simpelmin/img/calendar-icons.svg
simpelmin/static/simpelmin/img/icon-addlink.svg
simpelmin/static/simpelmin/img/icon-alert.svg
simpelmin/static/simpelmin/img/icon-calendar.svg
simpelmin/static/simpelmin/img/icon-changelink.svg
simpelmin/static/simpelmin/img/icon-clock.svg
simpelmin/static/simpelmin/img/icon-no.svg
simpelmin/static/simpelmin/img/icon-unknown-alt.svg
simpelmin/static/simpelmin/img/icon-unknown.svg
simpelmin/static/simpelmin/img/icon-yes.svg
simpelmin/static/simpelmin/img/inline-delete.svg
simpelmin/static/simpelmin/img/search.svg
simpelmin/static/simpelmin/img/selector-icons.svg
simpelmin/static/simpelmin/img/sorting-icons.svg
simpelmin/static/simpelmin/img/avatars/avatar_female.png
simpelmin/static/simpelmin/img/avatars/avatar_male.png
simpelmin/static/simpelmin/img/backgrounds/background-big.svg
simpelmin/static/simpelmin/img/backgrounds/background1.svg
simpelmin/static/simpelmin/img/django/LICENSE
simpelmin/static/simpelmin/img/django/README.txt
simpelmin/static/simpelmin/img/django/calendar-icons.svg
simpelmin/static/simpelmin/img/django/cart_bg_sm_blue.png
simpelmin/static/simpelmin/img/django/icon-addlink.svg
simpelmin/static/simpelmin/img/django/icon-alert.svg
simpelmin/static/simpelmin/img/django/icon-calendar.svg
simpelmin/static/simpelmin/img/django/icon-changelink.svg
simpelmin/static/simpelmin/img/django/icon-clock.svg
simpelmin/static/simpelmin/img/django/icon-deletelink.svg
simpelmin-1.0.1.dist-info/LICENSE
simpelmin-1.0.1.dist-info/METADATA
simpelmin-1.0.1.dist-info/WHEEL
simpelmin-1.0.1.dist-info/top_level.txt
simpelmin-1.0.1.dist-info/RECORD
